pysimpleini/__init__.py
pysimpleini/__main__.py
pysimpleini/document.py
pysimpleini/exceptions.py
pysimpleini/keys.py
pysimpleini/py.typed
pysimpleini/sections.py
pysimpleini/simpleini.py
pysimpleini/walker.py
pysimpleini-0.4.4.dist-info/LICENSE.md
pysimpleini-0.4.4.dist-info/METADATA
pysimpleini-0.4.4.dist-info/WHEEL
pysimpleini-0.4.4.dist-info/entry_points.txt
pysimpleini-0.4.4.dist-info/top_level.txt
pysimpleini-0.4.4.dist-info/RECORD
